napari_segment_blobs_and_things_with_membranes/__init__.py
napari_segment_blobs_and_things_with_membranes/_bia_bob_plugins.py
napari_segment_blobs_and_things_with_membranes/_tests/__init__.py
napari_segment_blobs_and_things_with_membranes/_tests/test_function.py
napari_segment_blobs_and_things_with_membranes-0.3.12.dist-info/LICENSE
napari_segment_blobs_and_things_with_membranes-0.3.12.dist-info/METADATA
napari_segment_blobs_and_things_with_membranes-0.3.12.dist-info/WHEEL
napari_segment_blobs_and_things_with_membranes-0.3.12.dist-info/entry_points.txt
napari_segment_blobs_and_things_with_membranes-0.3.12.dist-info/top_level.txt
napari_segment_blobs_and_things_with_membranes-0.3.12.dist-info/RECORD
