Metadata-Version: 2.1
Name: napari-segment-blobs-and-things-with-membranes
Version: 0.3.12
Summary: A plugin based on scikit-image for segmenting nuclei and cells based on fluorescent microscopy images with high intensity in nuclei and/or membranes
Home-page: https://github.com/haesleinhuepf/napari-segment-blobs-and-things-with-membranes
Author: Robert Haase
Author-email: robert.haase@tu-dresden.de
License: BSD-3-Clause
Project-URL: Bug Tracker, https://github.com/haesleinhuepf/napari-segment-blobs-and-things-with-membranes/issues
Project-URL: Documentation, https://github.com/haesleinhuepf/napari-segment-blobs-and-things-with-membranes#README.md
Project-URL: Source Code, https://github.com/haesleinhuepf/napari-segment-blobs-and-things-with-membranes
Project-URL: User Support, https://github.com/haesleinhuepf/napari-segment-blobs-and-things-with-membranes/issues
Classifier: Development Status :: 3 - Alpha
Classifier: Intended Audience :: Science/Research
Classifier: Framework :: napari
Classifier: Topic :: Scientific/Engineering :: Image Processing
Classifier: Topic :: Scientific/Engineering :: Information Analysis
Classifier: Programming Language :: Python
Classifier: Programming Language :: Python :: 3
Classifier: Programming Language :: Python :: 3.8
Classifier: Programming Language :: Python :: 3.9
Classifier: Programming Language :: Python :: 3.10
Classifier: Operating System :: OS Independent
Classifier: License :: OSI Approved :: BSD License
Requires-Python: >=3.8
License-File: LICENSE
Requires-Dist: napari-plugin-engine>=0.1.4
Requires-Dist: numpy
Requires-Dist: scikit-image
Requires-Dist: scipy
Requires-Dist: napari-tools-menu>=0.1.17
Requires-Dist: napari-time-slicer>=0.4.8
Requires-Dist: napari-assistant
Requires-Dist: stackview>=0.9.1
